boy/__init__.py
boy/call_me.py
ymj_test-0.1.dist-info/METADATA
ymj_test-0.1.dist-info/WHEEL
ymj_test-0.1.dist-info/top_level.txt
ymj_test-0.1.dist-info/RECORD
