Metadata-Version: 2.1
Name: ymj-test
Version: 0.1
Summary: i am ymj from gzist
Author: ymj
License: UNKNOWN
Platform: UNKNOWN
